[
  {
    "city": "Bangkok",
    "country": "Thailand",
    "imageId": "bangkok"
  },
  {
    "city": "Beijing",
    "country": "Tiongkok",
    "imageId": "beijing"
  },
  {
    "city": "Jakarta",
    "country": "Indonesia",
    "imageId": "jakarta"
  },
  {
    "city": "London",
    "country": "England",
    "imageId": "london"
  },
  {
    "city": "Paris",
    "country": "Prancis",
    "imageId": "paris"
  },
  {
    "city": "Singapura",
    "country": "Singapura",
    "imageId": "singapura"
  },
  {
    "city": "Tokyo",
    "country": "Japan",
    "imageId": "tokyo"
  },
  {
    "city": "Barcelona",
    "country": "Spanyol",
    "imageId": "barcelona"
  },
  {
    "city": "Madrid",
    "country": "Spanyol",
    "imageId": "madrid"
  },
  {
    "city": "New Delhi",
    "country": "India",
    "imageId": "newdelhi"
  },
  {
    "city": "Osaka",
    "country": "Japan",
    "imageId": "osaka"
  },
  {
    "city": "Soeul",
    "country": "Korea Selatan",
    "imageId": "soeul"
  },
  {
    "city": "Washington",
    "country": "Amerika Serikat",
    "imageId": "washington"
  }
]
